wbreakpoint/__init__.py
wbreakpoint/test.py
wbreakpoint/wb.py
wbreakpoint-1.0.0.dist-info/LICENCE.txt
wbreakpoint-1.0.0.dist-info/METADATA
wbreakpoint-1.0.0.dist-info/WHEEL
wbreakpoint-1.0.0.dist-info/top_level.txt
wbreakpoint-1.0.0.dist-info/RECORD
