Metadata-Version: 2.1
Name: wbreakpoint
Version: 1.0.0
Summary: Breakpoint as a wrapper
Home-page: https://github.com/ogiles1999/wbreakpoint
Author: Oliver Giles
Author-email: ogiles@email.com
License: UNKNOWN
Project-URL: Bug Tracker, https://github.com/ogiles1999/wbreakpoint/issues
Platform: UNKNOWN
Classifier: Programming Language :: Python :: 3
Classifier: License :: OSI Approved :: MIT License
Classifier: Operating System :: OS Independent
Requires-Python: >=3.6
License-File: LICENCE.txt
